design.plone.opendata-1.0.0a0-py3.11-nspkg.pth
design/plone/opendata/__init__.py
design/plone/opendata/configure.zcml
design/plone/opendata/dependencies.zcml
design/plone/opendata/interfaces.py
design/plone/opendata/permissions.zcml
design/plone/opendata/profiles.zcml
design/plone/opendata/testing.py
design/plone/opendata/browser/__init__.py
design/plone/opendata/browser/configure.zcml
design/plone/opendata/browser/dcatapit.py
design/plone/opendata/content/__init__.py
design/plone/opendata/content/dataset.py
design/plone/opendata/controlpanel/__init__.py
design/plone/opendata/controlpanel/configure.zcml
design/plone/opendata/controlpanel/opendata.py
design/plone/opendata/indexers/__init__.py
design/plone/opendata/indexers/configure.zcml
design/plone/opendata/locales/__init__.py
design/plone/opendata/locales/design.plone.opendata.pot
design/plone/opendata/locales/manual.pot
design/plone/opendata/locales/update.sh
design/plone/opendata/locales/en/LC_MESSAGES/design.plone.opendata.po
design/plone/opendata/locales/it/LC_MESSAGES/design.plone.opendata.po
design/plone/opendata/profiles/default/browserlayer.xml
design/plone/opendata/profiles/default/catalog.xml
design/plone/opendata/profiles/default/controlpanel.xml
design/plone/opendata/profiles/default/diff_tool.xml
design/plone/opendata/profiles/default/metadata.xml
design/plone/opendata/profiles/default/repositorytool.xml
design/plone/opendata/profiles/default/rolemap.xml
design/plone/opendata/profiles/default/theme.xml
design/plone/opendata/profiles/default/types.xml
design/plone/opendata/profiles/default/registry/main.xml
design/plone/opendata/profiles/default/types/OpendataDataset.xml
design/plone/opendata/profiles/initial/metadata.xml
design/plone/opendata/profiles/uninstall/browserlayer.xml
design/plone/opendata/serializers/__init__.py
design/plone/opendata/serializers/configure.zcml
design/plone/opendata/serializers/summary.py
design/plone/opendata/setuphandlers/__init__.py
design.plone.opendata-1.0.0a0.dist-info/LICENSE.GPL
design.plone.opendata-1.0.0a0.dist-info/LICENSE.md
design.plone.opendata-1.0.0a0.dist-info/METADATA
design.plone.opendata-1.0.0a0.dist-info/WHEEL
design.plone.opendata-1.0.0a0.dist-info/entry_points.txt
design.plone.opendata-1.0.0a0.dist-info/namespace_packages.txt
design.plone.opendata-1.0.0a0.dist-info/top_level.txt
design.plone.opendata-1.0.0a0.dist-info/RECORD
