Metadata-Version: 2.2
Name: design.plone.opendata
Version: 1.0.0a0
Summary: Plone DCAT IT
Home-page: https://github.com/RedTurtle/design.plone.opendata
Author: RedTurtle
Author-email: info@redturtle.it
License: GPL version 2
Project-URL: PyPI, https://pypi.org/project/design.plone.opendata
Project-URL: Source, https://github.com/RedTurtle/design.plone.opendata
Project-URL: Tracker, https://github.com/RedTurtle/design.plone.opendata/issues
Keywords: Python Plone CMS
Classifier: Development Status :: 3 - Alpha
Classifier: Environment :: Web Environment
Classifier: Framework :: Plone
Classifier: Framework :: Plone :: Addon
Classifier: Framework :: Plone :: 6.0
Classifier: Programming Language :: Python
Classifier: Programming Language :: Python :: 3.10
Classifier: Programming Language :: Python :: 3.11
Classifier: Programming Language :: Python :: 3.12
Classifier: Programming Language :: Python :: 3.13
Classifier: Operating System :: OS Independent
Classifier: License :: OSI Approved :: GNU General Public License v2 (GPLv2)
Requires-Python: >=3.10
License-File: LICENSE.GPL
License-File: LICENSE.md
Requires-Dist: setuptools
Requires-Dist: Plone
Requires-Dist: plone.api
Requires-Dist: plone.restapi
Requires-Dist: rdflib
Provides-Extra: test
Requires-Dist: zest.releaser[recommended]; extra == "test"
Requires-Dist: zestreleaser.towncrier; extra == "test"
Requires-Dist: plone.app.testing; extra == "test"
Requires-Dist: plone.restapi[test]; extra == "test"
Requires-Dist: pytest; extra == "test"
Requires-Dist: pytest-cov; extra == "test"
Requires-Dist: pytest-plone>=0.5.0; extra == "test"
Dynamic: author
Dynamic: author-email
Dynamic: classifier
Dynamic: description
Dynamic: description-content-type
Dynamic: home-page
Dynamic: keywords
Dynamic: license
Dynamic: project-url
Dynamic: provides-extra
Dynamic: requires-dist
Dynamic: requires-python
Dynamic: summary
